README.md
setup.py
SI1145/SI1145.py
SI1145/__init__.py
SI1145.egg-info/PKG-INFO
SI1145.egg-info/SOURCES.txt
SI1145.egg-info/dependency_links.txt
SI1145.egg-info/requires.txt
SI1145.egg-info/top_level.txt